AUTHORS.md
LICENSE
README.md
setup.py
metadrive/__init__.py
metadrive/_requests.py
metadrive/_selenium.py
metadrive/_xarray.py
metadrive/auth.py
metadrive/cli.py
metadrive/config.py
metadrive/drivers.py
metadrive/drives.py
metadrive/helpers.py
metadrive/mixins.py
metadrive/mnt.py
metadrive/tasks.py
metadrive/utils.py
metadrive.egg-info/PKG-INFO
metadrive.egg-info/SOURCES.txt
metadrive.egg-info/dependency_links.txt
metadrive.egg-info/entry_points.txt
metadrive.egg-info/not-zip-safe
metadrive.egg-info/requires.txt
metadrive.egg-info/top_level.txt
metadrive/tests/__init__.py
metadrive/tests/test_wrapper.py